.bumpversion.cfg
.readthedocs.yaml
LICENSE
MANIFEST.in
Makefile
README.md
conftest.py
pyproject.toml
setup.py
docs/.readthedocs.yaml
docs/CONTRIBUTING.md
docs/Makefile
docs/README.md
docs/conf.py
docs/get_player_game_log.md
docs/get_team_game_log.md
docs/index.md
docs/make.bat
docs/player_splits.md
docs/requirements.txt
docs/team_splits.md
docs/source/modules.rst
docs/source/pro_football_reference_web_scraper.rst
pro_football_reference_web_scraper/__init__.py
pro_football_reference_web_scraper/_version.py
pro_football_reference_web_scraper/player_game_log.py
pro_football_reference_web_scraper/player_splits.py
pro_football_reference_web_scraper/team_game_log.py
pro_football_reference_web_scraper/team_splits.py
pro_football_reference_web_scraper.egg-info/PKG-INFO
pro_football_reference_web_scraper.egg-info/SOURCES.txt
pro_football_reference_web_scraper.egg-info/dependency_links.txt
pro_football_reference_web_scraper.egg-info/requires.txt
pro_football_reference_web_scraper.egg-info/top_level.txt
tests/test_player_game_log_integration.py
tests/test_player_game_log_unit.py
tests/test_player_splits_integration.py
tests/test_player_splits_unit.py
tests/test_team_game_log_integration.py
tests/test_team_game_log_unit.py
tests/test_team_splits_integration.py
tests/test_team_splits_unit.py