Metadata-Version: 2.1
Name: pro-football-reference-web-scraper
Version: 0.2.1
Summary: Stats web scraper of Pro Football Reference
Author-email: Matthew Kim <mjk2244@columbia.edu>
License:                                  Apache License
Project-URL: repository, https://github.com/mjk2244/pro-football-reference-web-scraper
Classifier: Development Status :: 2 - Pre-Alpha
Classifier: Programming Language :: Python :: Implementation :: CPython
Classifier: Programming Language :: Python :: Implementation :: PyPy
Classifier: Programming Language :: Python :: 3
Classifier: Programming Language :: Python :: 3.7
Classifier: Programming Language :: Python :: 3.8
Classifier: Programming Language :: Python :: 3.9
Classifier: Programming Language :: Python :: 3.10
Classifier: Programming Language :: Python :: 3.11
Requires-Python: >=3.8
Provides-Extra: develop
License-File: LICENSE
